aiohttp_webpack/__init__.py
aiohttp_webpack-0.0.7.dist-info/METADATA
aiohttp_webpack-0.0.7.dist-info/WHEEL
aiohttp_webpack-0.0.7.dist-info/top_level.txt
aiohttp_webpack-0.0.7.dist-info/RECORD
