Metadata-Version: 2.1
Name: aiohttp-webpack
Version: 0.0.7
Summary: Utility for load static in AioHttp web framework from Webpack with help of webpack-bundle-tracker JS plugin.
Home-page: https://pypi.org/project/aiohttp-webpack/
Author: Filantus
Author-email: filantus@mail.ru
License: GPL
Platform: UNKNOWN
Classifier: Intended Audience :: Developers
Classifier: License :: OSI Approved :: GNU General Public License (GPL)
Classifier: Programming Language :: Python :: 3.7
Classifier: Operating System :: OS Independent
Requires-Dist: aiohttp
